dotlocalslashbin.py
dotlocalslashbin-0.0.25.dist-info/METADATA
dotlocalslashbin-0.0.25.dist-info/WHEEL
dotlocalslashbin-0.0.25.dist-info/entry_points.txt
dotlocalslashbin-0.0.25.dist-info/licenses/LICENSES/MPL-2.0.txt
dotlocalslashbin-0.0.25.dist-info/RECORD
