Metadata-Version: 2.4
Name: dotlocalslashbin
Version: 0.0.25
Summary: Download and extract files to `~/.local/bin/`.
Author-email: Keith Maxwell <keith.maxwell@gmail.com>
Requires-Python: >=3.11
Classifier: Programming Language :: Python :: 3
Classifier: License :: OSI Approved :: Mozilla Public License 2.0 (MPL 2.0)
License-File: LICENSES/MPL-2.0.txt
Requires-Dist: black ; extra == "test"
Requires-Dist: codespell ; extra == "test"
Requires-Dist: flit ; extra == "test"
Requires-Dist: mypy ; extra == "test"
Requires-Dist: nox ; extra == "test"
Requires-Dist: pytest ; extra == "test"
Requires-Dist: reuse ; extra == "test"
Requires-Dist: ruff ; extra == "test"
Requires-Dist: twine ; extra == "test"
Requires-Dist: usort ; extra == "test"
Requires-Dist: yamllint ; extra == "test"
Project-URL: Home, https://github.com/maxwell-k/dotlocalslashbin/
Provides-Extra: test
